ifkit/__init__.py
ifkit/__version__.py
ifkit/csv.py
ifkit/excel.py
ifkit/json_encoder.py
ifkit/mq.py
ifkit/mysql_all_tables.py
ifkit/mysql_create_table_statement.py
ifkit/mysql_export_excel.py
ifkit/qyweixin.py
ifkit/sms.py
ifkit/txt.py
ifkit/user_agent_parser.py
ifkit-0.1.59.dist-info/licenses/LICENSE
ifkit-0.1.59.dist-info/METADATA
ifkit-0.1.59.dist-info/WHEEL
ifkit-0.1.59.dist-info/top_level.txt
ifkit-0.1.59.dist-info/RECORD
