Metadata-Version: 2.4
Name: ifkit
Version: 0.1.59
Summary: 日常工作使用的小工具/小功能
Home-page: https://www.infuq.com
Author: infuq
Author-email: v-infuq@outlook.com
License: MIT
Classifier: License :: OSI Approved :: MIT License
Classifier: Programming Language :: Python
Classifier: Programming Language :: Python :: 3
Classifier: Programming Language :: Python :: 3.6
Classifier: Programming Language :: Python :: Implementation :: CPython
Classifier: Programming Language :: Python :: Implementation :: PyPy
Requires-Python: >=3.6.0
License-File: LICENSE
Requires-Dist: mq_http_sdk>=1.0.3
Requires-Dist: openpyxl>=3.0.10
Requires-Dist: PyMySQL>=1.1.1
Requires-Dist: Requests>=2.32.5
Requires-Dist: user_agents>=2.2.0
Requires-Dist: xlrd>=2.0.1
Requires-Dist: xlwt>=1.3.0
Dynamic: author
Dynamic: author-email
Dynamic: classifier
Dynamic: description
Dynamic: description-content-type
Dynamic: home-page
Dynamic: license
Dynamic: license-file
Dynamic: requires-dist
Dynamic: requires-python
Dynamic: summary
